clope/__init__.py
clope/snow/__init__.py
clope/snow/connection_handling.py
clope/snow/dates.py
clope/snow/dimensions.py
clope/snow/facts.py
clope/snow/functions.py
clope/spotlight/__init__.py
clope/spotlight/spotlight.py
clope-0.2.2.dist-info/WHEEL
clope-0.2.2.dist-info/METADATA
clope-0.2.2.dist-info/RECORD
