Metadata-Version: 2.3
Name: clope
Version: 0.2.2
Summary: Python package for interacting with the Cantaloupe/Seed vending system. Primarily the Spotlight API.
Author: Jordan Maynor
Author-email: Jordan Maynor <jmaynor@pepsimidamerica.com>
License: This is free and unencumbered software released into the public domain.
Classifier: Programming Language :: Python :: 3
Classifier: License :: OSI Approved :: The Unlicense (Unlicense)
Classifier: Operating System :: OS Independent
Requires-Dist: aiohttp
Requires-Dist: openpyxl
Requires-Dist: pandas
Requires-Dist: requests
Requires-Dist: snowflake-connector-python[pandas]>=4.0.0
Requires-Dist: tenacity
Requires-Python: >=3.12
Project-URL: Homepage, https://github.com/pepsimidamerica/clope
